pandoc_plantuml_filter.py
pandoc_plantuml_filter-0.1.5.dist-info/LICENSE
pandoc_plantuml_filter-0.1.5.dist-info/METADATA
pandoc_plantuml_filter-0.1.5.dist-info/WHEEL
pandoc_plantuml_filter-0.1.5.dist-info/entry_points.txt
pandoc_plantuml_filter-0.1.5.dist-info/top_level.txt
pandoc_plantuml_filter-0.1.5.dist-info/RECORD
